<?xml version="1.0" encoding="UTF-8"?>
<objects serializationModel="Studio.02.03.00">
	<object class="AudioFile" id="{9d5154d4-a448-4364-a2cc-16b939e8d545}">
		<property name="assetPath">
			<value>Character/Talking/maincharacter0.wav</value>
		</property>
		<property name="frequencyInKHz">
			<value>44.0999985</value>
		</property>
		<property name="channelCount">
			<value>1</value>
		</property>
		<property name="length">
			<value>3.1655782312925171</value>
		</property>
		<relationship name="masterAssetFolder">
			<destination>{76f1460c-200b-47e5-a811-8119118438b9}</destination>
		</relationship>
	</object>
</objects>
