<?xml version="1.0" encoding="UTF-8"?>
<objects serializationModel="Studio.02.03.00">
	<object class="AudioFile" id="{d7ca79c4-59d5-4c70-9f79-004f022cda41}">
		<property name="assetPath">
			<value>wooden-chair-over-tiles.wav</value>
		</property>
		<property name="isStreaming">
			<value>true</value>
		</property>
		<property name="frequencyInKHz">
			<value>48</value>
		</property>
		<property name="channelCount">
			<value>2</value>
		</property>
		<property name="length">
			<value>17.5</value>
		</property>
		<relationship name="masterAssetFolder">
			<destination>{76f1460c-200b-47e5-a811-8119118438b9}</destination>
		</relationship>
	</object>
</objects>
